{"uid":"5708916163870720","recipient":{"type":"email","hashed":true,"salt":"dentalprocess.pl","identity":"sha256$f97c2b7e1351ffd542b00e8f701f453f3e5baab4fc4ee8df533d2763354993a7"},"image":"https://dentalprocess.pl/participant/5708916163870720/xassist-badge.png","evidence":"https://dentalprocess.pl/participant/5708916163870720","issuedOn":1516471388999,"badge":"https://dentalprocess.pl/xassist/xassist-ref-badge.json","verify":{"type":"hosted","url":"https://dentalprocess.pl/participant/5708916163870720/xassist-badge.json"}}