{"uid":"5729458187141120","recipient":{"type":"email","hashed":true,"salt":"dentalprocess.pl","identity":"sha256$4ef89c4dd7e060b8c2cf05e65fd5d265e861f8f388d903c1d6b0306a003b0662"},"image":"https://dentalprocess.pl/participant/5729458187141120/orthoday-badge.png","evidence":"https://dentalprocess.pl/participant/5729458187141120","issuedOn":1508605702268,"badge":"https://dentalprocess.pl/orthoday/orthoday-ref-badge.json","verify":{"type":"hosted","url":"https://dentalprocess.pl/participant/5729458187141120/orthoday-badge.json"}}